{
  "name": "The Anarchist Cookbook",
  "system": {
    "origin": "",
    "effect": "The simple act of owning this book isn’t illegal, but carrying out its suggestions might be.\n\nRank 1 - Novice Technology Education: Whenever you apply a Repel to a target, they become Blinded until the end of their next turn. This may only affect a target once per Scene.\nRank 2 - Expert Technology Education: Whenever you hit a target with a Repel or Pester Ball, they lose Hit Points equal to your Technology Education Rank.",
    "snippet": "",
    "rules": [],
    "slug": null,
    "schema": {
      "version": 0.11,
      "lastMigration": {
        "datetime": "2023-08-16T07:27:02.424Z",
        "version": {
          "schema": null,
          "foundry": "11.307",
          "system": "4.0.0.alpha.4"
        }
      }
    },
    "referenceEffect": "",
    "quantity": "1",
    "category": "",
    "cost": "1000",
    "consumable": "0",
    "subtype": "",
    "container": false,
    "automation": [],
    "name": "The Anarchist Cookbook",
    "useCount": 0
  },
  "type": "item",
  "img": "/systems/ptu/css/images/icons/item_icon.png",
  "effects": [],
  "ownership": {
    "default": 0,
    "DsHOL7PqMABKgssN": 3
  },
  "flags": {},
  "_stats": {
    "systemId": "ptu",
    "systemVersion": "4.0.0.beta.3",
    "coreVersion": "11.308",
    "createdTime": 1683368825386,
    "modifiedTime": 1695027515118,
    "lastModifiedBy": "ODt7FhFvbVjW9f1k"
  },
  "folder": null,
  "sort": 0,
  "_id": "YK96vKhkjGw6xoMU",
  "_key": "!items!YK96vKhkjGw6xoMU"
}