{
  "name": "TM125 - Stored Power",
  "type": "item",
  "system": {
    "origin": "",
    "effect": "For every Combat Stage the user has above 0, add 2 to Stored Power's Damage Base, up to a maximum of Damage Base 20.",
    "snippet": "",
    "rules": [],
    "slug": null,
    "schema": {
      "version": null,
      "lastMigration": null
    },
    "automation": [],
    "quantity": 1,
    "category": "",
    "cost": null,
    "consumable": true,
    "subtype": "",
    "container": false
  },
  "_id": "VpoShCtjnkUZqz5e",
  "img": "systems/ptu/static/images/item_icons/tm.webp",
  "effects": [],
  "folder": null,
  "sort": 0,
  "ownership": {
    "default": 0,
    "ODt7FhFvbVjW9f1k": 3
  },
  "flags": {},
  "_stats": {
    "systemId": "ptu",
    "systemVersion": "4.0.0.alpha.10",
    "coreVersion": "11.307",
    "createdTime": 1692967648964,
    "modifiedTime": 1692967650119,
    "lastModifiedBy": "ODt7FhFvbVjW9f1k"
  },
  "_key": "!items!VpoShCtjnkUZqz5e"
}