{
  "name": "Mountain",
  "description": "A generated habitat table",
  "results": [
    "WRZjALNAN1BVMfCZ",
    "Recrw57SjdRejhEc",
    "vZ1qiySR65JzDt8W",
    "ZDr3hTEuSDmntxAo",
    "m8WC9jle9VIOEwtq",
    "SEt5nzpaFVNyGSp8",
    "iXBQ1cga61fHNTWi",
    "E17kj6Ru3n27Z8oy",
    "AZXIif9XlfPm3oIh",
    "e5kWH0KsKSxWxQSA",
    "Pv6edE0ZIPwPHxvJ",
    "tzXytjqg2zPjORg7",
    "Ar2eg4QtgnU80ZA7",
    "4nttN1KbODAIleBR",
    "tbgxpfaRnhrHqjp3",
    "EObgF30qc9nfJ4Bt",
    "O9DDF18hQKuh8AEo",
    "w64CA0XbMam4YVaA",
    "SlkOUB7FXQq7Lug9",
    "1KW9fdZonMjtagNf",
    "JxuHqom3IDZTU1Wz",
    "9v6ofhoyRrcxeuIp",
    "IyBnarppcmIgwAvA",
    "f1utqucVTKIuH9YX",
    "O9ZGzHbVLOGS3Ysn",
    "QzOxUjoDvP141kOG",
    "43Tqvf5JdqOXOWIS",
    "bdFa0UWgAqTCmg7D",
    "lONDB9YZco6FVPk4",
    "9rI5aJ0jrFacvV46",
    "dxL3sQzUMQDWBpm2",
    "EWDHSlqkcS1XVonU",
    "yyD5uSaBUiSMvLuY",
    "4BZgZuZtk1VvDAlj",
    "V9uRiiGZSa3EZ7CH",
    "LvMETUSqlMkyf7uE",
    "w7DFP8wtH8yx7idL",
    "BevABma8Img4xI1s",
    "bII85ZqJc0kmUeYC",
    "6kxUYmY7LQ1jjL1w",
    "SBuYV3VpKHgLnxR1",
    "SK8dFOpSaMvlwQIE",
    "tKa60WnzoEYYcB8y",
    "syyEQyuoRtrzyUCn",
    "h0IxWcQWytFLvWbD",
    "nENwv8pjBZdE0QSU",
    "UAC9KY39SrB5UAjv",
    "Z3116Q6xAqa6Sr7X",
    "xfFfYZ6HpeQi5sGP",
    "tYvoGaFliAqV8G2z",
    "EvnFtVV766swkDRe",
    "RZ5SuNTiVItGpPu5",
    "wtUwur7uBSTwQK9T",
    "17xnA0ntG47ZSnti",
    "MRUHJH4pZ4mrHN84",
    "1sg5tW8z5PcbfGzc",
    "amLJZkPi4zqrA7wA",
    "rcyZGOfU9X37Ten3",
    "sT4QGcVbPbyqVXZ6",
    "Hb57DSGM5BEBagMS",
    "R3m7i6M5XTQMNHOk",
    "rIANDRLWIFXcEWzj",
    "pNM6iBvEoZECIeh6",
    "KEDtqwdUOjTWAFMU",
    "G4S7jaHtbl114Hx0",
    "BUOB3GRQYr0JptCW",
    "qPMcpI5ZyllXXI98",
    "wOsjIOuJGOVpBN0N",
    "kOt8pbQKGoAjGH3s",
    "gIVf3EPdCckOqYnN",
    "jxQ4YHFoAesiWPN8",
    "Xvt3iYQVc3OHuuBv",
    "rABsvSXJkA26gM5f",
    "xxGP0Z2WgHK47Xoh",
    "JRbVpen7vPmjPspV",
    "j1WkKh06dwR1dJd4",
    "ZiR5o5Jxh0lGBAfp",
    "WZGcSW0AUUolvoM3",
    "gmaWmI27iLJIFxhD",
    "3lxLgDDPHc9jzPAN",
    "f3t8iA4sncMwtdUv",
    "iraHQaHvx55om8Yy",
    "TgLw6sG5a9sURGlV",
    "HLzFkgc70CHVq4w4",
    "kvCvPUrzMAURfm2v",
    "ENYwobYOHY8f5Js0",
    "E2WNG8mK04BlpilU",
    "S90u2HMh7EVbPc8z",
    "BI0xm0rTERvS3IKP",
    "a35MejowXTgxdLKC",
    "1trGn3bwR2nUa5lB",
    "Z4Q6cG1xFieMgwCE",
    "Jbzq9iKvgIWiteaS",
    "Gll7Wxp31dQq5nbE",
    "4TEi4XVqhuElU8bc",
    "lEBIr1J4VcG1qGrI",
    "Kg7s4FfUzhueGIt6",
    "btPih3vNcbPWnvIP",
    "zduYPexvtv2k8WqM",
    "GalJptHkJNmMotro",
    "x6tNty4kHMrFIEjL",
    "miBVhdPeUuUI4v5G",
    "ovAbwYr1NwzW1Xox",
    "VR47anmN7S8UCxl4",
    "ztSBveO6eeWB0Ncs",
    "vTFdF5CphhfADOJV",
    "DyuUTePNzIA5Lj0o",
    "sMVkHk3T5jS4wgLZ",
    "9AcXn3RHocZiVnrD",
    "CtRmJXAaVfNIRHks",
    "NQXvjkmNcq15ZxMh",
    "SmYCx2orrpEzgPlk",
    "TWHqIPLSb4j91uck",
    "uFICwE1XRmvd0tON",
    "Iayl4Fczu4meKxKr",
    "RW40QO2GzZqKZ2pg",
    "vHTEkN0aUllUtQsV",
    "xSokbq62UvBtjcHf",
    "CF8DgWkkJx1ltnYN",
    "fCEAWVCFnAdV2OEQ",
    "DiHSluhyIjtxMCrT",
    "WkKkv0SAFHBcMKfK",
    "G47fLcnxKjDpmkM4",
    "EVJghbzQCwRwcxMJ",
    "SyJCFeTCUnxEMsSY",
    "PrKO0yifZAwlmskC",
    "4Kg9vJEo9QRrlGlh",
    "IYB889M8UjhG2RpD",
    "TkFsgkuthEYivAgQ",
    "jz1vW5gDIVmGAY1o",
    "y089cccUheEgtVb1",
    "Hpq0KKM16YlY4AdG"
  ],
  "formula": "1d132",
  "_id": "mpDySQbu2WjGZbOJ",
  "img": "icons/svg/d20-grey.svg",
  "replacement": true,
  "displayRoll": true,
  "folder": null,
  "sort": 0,
  "ownership": {
    "default": 0,
    "ODt7FhFvbVjW9f1k": 3
  },
  "flags": {},
  "_stats": {
    "systemId": "ptu",
    "systemVersion": "4.0.0.alpha.15",
    "coreVersion": "11.308",
    "createdTime": 1693317666238,
    "modifiedTime": 1693317824022,
    "lastModifiedBy": "ODt7FhFvbVjW9f1k"
  },
  "_key": "!tables!mpDySQbu2WjGZbOJ"
}