{
  "name": "Innovation",
  "system": {
    "origin": "",
    "effect": "Target: A Pokémon with at least 1 Tutor Point.\nEffect: The target loses 1 Tutor Point, and then learns a Move created with Innovation. See the next section on page 84 for details on creating Moves for this Feature. A Pokémon may only have one Move created by Innovation at a time.",
    "snippet": "",
    "rules": [],
    "enabled": true,
    "slug": null,
    "schema": {
      "version": 0.11,
      "lastMigration": null
    },
    "referenceEffect": "",
    "source": {
      "value": "PTR Compendiums"
    },
    "stackSlugs": false,
    "keywords": [],
    "prerequisites": [
      "Adaptable Performance"
    ],
    "frequency": "Daily - Extended Action",
    "notes": "",
    "free": false,
    "class": "Coordinator",
    "name": "Innovation",
    "useCount": 0,
    "automation": []
  },
  "type": "feat",
  "img": "/systems/ptu/css/images/icons/feat_icon.png",
  "effects": [],
  "ownership": {
    "default": 0,
    "DsHOL7PqMABKgssN": 3
  },
  "flags": {
    "core": {
      "sourceId": "Compendium.ptu.feats.l4HuDSNb6UfMWjvV"
    },
    "ptu": {
      "prereqBackup": "Adaptable Performance"
    }
  },
  "_stats": {
    "systemId": "ptu",
    "systemVersion": "4.1.4",
    "coreVersion": "12.318",
    "createdTime": 1683368081797,
    "modifiedTime": 1707818613949,
    "lastModifiedBy": "ODt7FhFvbVjW9f1k"
  },
  "folder": null,
  "sort": 18700000,
  "_id": "HynpVK8BeHRY7tnu",
  "_key": "!items!HynpVK8BeHRY7tnu"
}
