{
  "name": "Moment of Action",
  "system": {
    "origin": "",
    "effect": "Target: Up to two Allied Trainers\nEffect: Each target gains 1 Temporary Action Point.\n These Action Points disappear after one full Round.",
    "snippet": "",
    "rules": [],
    "slug": null,
    "schema": {
      "version": 0.11,
      "lastMigration": null
    },
    "referenceEffect": "",
    "prerequisites": "Cheerleader",
    "frequency": "At-Will – Standard Action",
    "tags": "[Orders]",
    "notes": "",
    "free": false,
    "class": "",
    "name": "Moment of Action",
    "useCount": 0,
    "automation": []
  },
  "type": "feat",
  "img": "/systems/ptu/css/images/icons/feat_icon.png",
  "effects": [],
  "ownership": {
    "default": 0,
    "DsHOL7PqMABKgssN": 3
  },
  "flags": {
    "core": {
      "sourceId": "Compendium.ptu.feats.2BiDq0OdwvHFTS9L"
    }
  },
  "_stats": {
    "systemId": "ptu",
    "systemVersion": "4.0.0.beta.3",
    "coreVersion": "11.308",
    "createdTime": 1683368079348,
    "modifiedTime": 1695027507910,
    "lastModifiedBy": "ODt7FhFvbVjW9f1k"
  },
  "folder": null,
  "sort": 50500000,
  "_id": "j2qRhnEKXGEGQQVO",
  "_key": "!items!j2qRhnEKXGEGQQVO"
}