{
  "name": "Survivalist",
  "system": {
    "name": "Survivalist",
    "origin": "",
    "effect": "Choose a Terrain in which you have spent at least three nights. You gain Naturewalk for that terrain and a +2 bonus to Athletics, Acrobatics, Stealth, Perception, and Survival Checks in that terrain. When you have 2 Survivalist Features, you may choose a second Terrain. When you have 4 Survivalist Features, you may choose a third terrain. When you have 6 Survivalist Features, you may choose a fourth terrain. The terrains are: Grassland, Forest, Wetlands, Ocean, Tundra, Mountain, Cave, Urban, Desert",
    "snippet": "",
    "useCount": 0,
    "automation": [],
    "prerequisites": "Novice Survival",
    "frequency": "One Time Use - Extended Action",
    "tags": "[Class][+HP]",
    "notes": "",
    "free": false
  },
  "type": "feat",
  "img": "/systems/ptu/css/images/icons/class_feat_icon.png",
  "effects": [],
  "ownership": {
    "default": 0,
    "DsHOL7PqMABKgssN": 3
  },
  "flags": {
    "core": {
      "sourceId": "Compendium.ptu.feats.6st7iizBrfRjgm8p"
    }
  },
  "_stats": {
    "systemId": "ptu",
    "systemVersion": "3.2.3.8",
    "coreVersion": "10.291",
    "createdTime": 1683368079024,
    "modifiedTime": 1683383582282,
    "lastModifiedBy": "DsHOL7PqMABKgssN"
  },
  "folder": null,
  "sort": 0,
  "_id": "zKDZMfjLUVSxhDcU",
  "_key": "!items!zKDZMfjLUVSxhDcU"
}