{
  "type": "species",
  "system": {
    "schema": {
      "version": 0.11,
      "lastMigration": {
        "datetime": "2023-08-15T11:56:04.256Z",
        "version": {
          "schema": null,
          "foundry": "11.307",
          "system": "0.21"
        }
      }
    },
    "dexentry": "",
    "number": 1664,
    "form": "",
    "stats": {
      "hp": 7,
      "atk": 10,
      "def": 13,
      "spatk": 7,
      "spdef": 8,
      "spd": 5
    },
    "types": [
      "Grass",
      "Poison"
    ],
    "abilities": {
      "basic": [
        {
          "slug": "liquid-ooze",
          "uuid": "Compendium.ptu.abilities.Item.4Eajhd1jemnWDwl9"
        },
        {
          "slug": "chlorophyll",
          "uuid": "Compendium.ptu.abilities.Item.ZiTUZHmZaIq0K2na"
        }
      ],
      "advanced": [
        {
          "slug": "leaf-guard",
          "uuid": "Compendium.ptu.abilities.Item.wwGnvLri2jpoS0RP"
        },
        {
          "slug": "harvest",
          "uuid": "Compendium.ptu.abilities.Item.7OIO6iaquGxiMRvw"
        }
      ],
      "high": [
        {
          "slug": "rattled",
          "uuid": "Compendium.ptu.abilities.Item.TcxNWzXMpxjBZbgo"
        }
      ]
    },
    "evolutions": [
      {
        "slug": "delta-dwebble-berry",
        "uuid": "Compendium.ptu.species.Item.ejnbwKD59u8Xn5Ym",
        "level": 1,
        "other": {
          "restrictions": []
        }
      },
      {
        "slug": "delta-crustle-berry",
        "uuid": "Compendium.ptu.species.Item.6pcKrPn2EgXcr0bQ",
        "level": 30,
        "other": {
          "restrictions": []
        }
      }
    ],
    "size": {
      "height": 1.4,
      "weight": 200,
      "sizeClass": "Medium",
      "weightClass": 6
    },
    "breeding": {
      "genderRatio": 50,
      "eggGroups": [
        "None"
      ],
      "hatchRate": -1
    },
    "diet": [
      "Herbivore"
    ],
    "habitats": [
      "Forest",
      "Grassland"
    ],
    "capabilities": {
      "overland": 5,
      "sky": 0,
      "swim": 1,
      "levitate": 0,
      "burrow": 0,
      "highJump": 1,
      "longJump": 1,
      "power": 5,
      "naturewalk": [
        "Forest"
      ],
      "other": [
        {
          "slug": "planter-berries",
          "uuid": "Compendium.ptu.capabilities.Item.YqHfwitF4fSQwn1s"
        }
      ]
    },
    "moves": {
      "level": [
        {
          "slug": "razor-leaf",
          "uuid": "Compendium.ptu.moves.Item.wYz4RubDs84tDVul",
          "level": 5
        },
        {
          "slug": "growth",
          "uuid": "Compendium.ptu.moves.Item.Bcv2CeJg9qU1q0Cb",
          "level": 7
        },
        {
          "slug": "leech-seed",
          "uuid": "Compendium.ptu.moves.Item.Jx4TeOVUk1DX8R45",
          "level": 11
        },
        {
          "slug": "barrage",
          "uuid": "Compendium.ptu.moves.Item.RaybG8UnxeR5oI9W",
          "level": 13
        },
        {
          "slug": "sludge",
          "uuid": "Compendium.ptu.moves.Item.5vPZfwNkmM0eKO03",
          "level": 17
        },
        {
          "slug": "stockpile",
          "uuid": "Compendium.ptu.moves.Item.VTgi7fLjJYUtu8GT",
          "level": 19
        },
        {
          "slug": "spit-up",
          "uuid": "Compendium.ptu.moves.Item.srUwReOeuVGAPTa5",
          "level": 19
        },
        {
          "slug": "swallow",
          "uuid": "Compendium.ptu.moves.Item.CbxiHzGex7oTghfX",
          "level": 19
        },
        {
          "slug": "leaf-tornado",
          "uuid": "Compendium.ptu.moves.Item.XKnzCG5ZGzGWMl5n",
          "level": 23
        },
        {
          "slug": "toxic-spikes",
          "uuid": "Compendium.ptu.moves.Item.LyEh7DPaMxvOwU3G",
          "level": 24
        },
        {
          "slug": "poison-jab",
          "uuid": "Compendium.ptu.moves.Item.TFFIb8CygY9dB625",
          "level": 29
        },
        {
          "slug": "slash",
          "uuid": "Compendium.ptu.moves.Item.sm3q5D8SkQcEmiGB",
          "level": 31
        },
        {
          "slug": "leaf-blade",
          "uuid": "Compendium.ptu.moves.Item.0wyKb3JsjxCnVsr6",
          "level": 38
        },
        {
          "slug": "ingrain",
          "uuid": "Compendium.ptu.moves.Item.2ky0KrGcz81tQ5X3",
          "level": 45
        },
        {
          "slug": "natural-gift",
          "uuid": "Compendium.ptu.moves.Item.rkPaIX8nSuJmwQiC",
          "level": 50
        },
        {
          "slug": "belch",
          "uuid": "Compendium.ptu.moves.Item.sv18it1VOb2zM9Gd",
          "level": 55
        }
      ],
      "machine": [
        {
          "slug": "work-up",
          "uuid": "Compendium.ptu.moves.Item.gCofXErMduyn6zwf"
        },
        {
          "slug": "dragon-claw",
          "uuid": "Compendium.ptu.moves.Item.ulXmidTSzjPqUrfI"
        },
        {
          "slug": "toxic",
          "uuid": "Compendium.ptu.moves.Item.eFxRUdqQgdnJybY4"
        },
        {
          "slug": "venoshock",
          "uuid": "Compendium.ptu.moves.Item.DKcoWwUTCJWg58nw"
        },
        {
          "slug": "hidden-power",
          "uuid": "Compendium.ptu.moves.Item.QyDgi8hL1jQLLhld"
        },
        {
          "slug": "sunny-day",
          "uuid": "Compendium.ptu.moves.Item.m787MkYyENqNyGOb"
        },
        {
          "slug": "hyper-beam",
          "uuid": "Compendium.ptu.moves.Item.WV86ctKatPhQpZC3"
        },
        {
          "slug": "protect",
          "uuid": "Compendium.ptu.moves.Item.HfiQ6I7xp7aGazV0"
        },
        {
          "slug": "frustration",
          "uuid": "Compendium.ptu.moves.Item.tkATQl42vxqWDfjd"
        },
        {
          "slug": "solar-beam",
          "uuid": "Compendium.ptu.moves.Item.Oa9NuYFi7yvPQTIO"
        },
        {
          "slug": "return",
          "uuid": "Compendium.ptu.moves.Item.eRjK7eB733bE0D8o"
        },
        {
          "slug": "double-team",
          "uuid": "Compendium.ptu.moves.Item.BHmRIX70tqHROfdN"
        },
        {
          "slug": "sludge-wave",
          "uuid": "Compendium.ptu.moves.Item.HisedpFvMgmEqsbV"
        },
        {
          "slug": "sludge-bomb",
          "uuid": "Compendium.ptu.moves.Item.T4KEAGNoEIpiO0G5"
        },
        {
          "slug": "aerial-ace",
          "uuid": "Compendium.ptu.moves.Item.9TD6e8JoZBjIuuAP"
        },
        {
          "slug": "facade",
          "uuid": "Compendium.ptu.moves.Item.QhQ2vUo3KMKo4Xou"
        },
        {
          "slug": "rest",
          "uuid": "Compendium.ptu.moves.Item.P0JIeR4lnilvg7K8"
        },
        {
          "slug": "attract",
          "uuid": "Compendium.ptu.moves.Item.0VI0E6oSQYULcSUU"
        },
        {
          "slug": "round",
          "uuid": "Compendium.ptu.moves.Item.GgdkAr3gDO6snP7r"
        },
        {
          "slug": "energy-ball",
          "uuid": "Compendium.ptu.moves.Item.GPc4UqyAsng4fPup"
        },
        {
          "slug": "shadow-claw",
          "uuid": "Compendium.ptu.moves.Item.pT1I4vwhSiqnVRkr"
        },
        {
          "slug": "smart-strike",
          "uuid": "Compendium.ptu.moves.Item.ImFfaRbYkW1fzPPL"
        },
        {
          "slug": "giga-impact",
          "uuid": "Compendium.ptu.moves.Item.WGOQso4iji1XKrdK"
        },
        {
          "slug": "swords-dance",
          "uuid": "Compendium.ptu.moves.Item.z5hgetbLhLvsd800"
        },
        {
          "slug": "fly",
          "uuid": "Compendium.ptu.moves.Item.TA3fevwvHn8PJHEI"
        },
        {
          "slug": "poison-jab",
          "uuid": "Compendium.ptu.moves.Item.TFFIb8CygY9dB625"
        },
        {
          "slug": "grass-knot",
          "uuid": "Compendium.ptu.moves.Item.jh2qDsk9mirEzqvu"
        },
        {
          "slug": "swagger",
          "uuid": "Compendium.ptu.moves.Item.arxy479cTjkB8mML"
        },
        {
          "slug": "sleep-talk",
          "uuid": "Compendium.ptu.moves.Item.Jfi9FN77Rplukh7W"
        },
        {
          "slug": "substitute",
          "uuid": "Compendium.ptu.moves.Item.IGk8nNBogMKp3seI"
        },
        {
          "slug": "snarl",
          "uuid": "Compendium.ptu.moves.Item.jVruXIDWy3HEHAeA"
        },
        {
          "slug": "nature-power",
          "uuid": "Compendium.ptu.moves.Item.FNtFpxkWjT9PhvEb"
        }
      ],
      "egg": [],
      "tutor": [
        {
          "slug": "acid",
          "uuid": "Compendium.ptu.moves.Item.Rj7PzPVf9YeEn5mG"
        },
        {
          "slug": "block",
          "uuid": "Compendium.ptu.moves.Item.PvmLk3AU04nOjH4x"
        },
        {
          "slug": "bug-bite",
          "uuid": "Compendium.ptu.moves.Item.NOJaY2kH3aQcaexD"
        },
        {
          "slug": "gastro-acid",
          "uuid": "Compendium.ptu.moves.Item.MDlLKeBdiKEtjK3o"
        },
        {
          "slug": "giga-drain",
          "uuid": "Compendium.ptu.moves.Item.mGvVlposKAYCa15m"
        },
        {
          "slug": "gunk-shot",
          "uuid": "Compendium.ptu.moves.Item.WBkN88g7D8ruzV02"
        },
        {
          "slug": "ingrain-n",
          "uuid": "Compendium.ptu.moves.Item.2ky0KrGcz81tQ5X3"
        },
        {
          "slug": "knock-off",
          "uuid": "Compendium.ptu.moves.Item.wXMLKSFvWlsa0ee6"
        },
        {
          "slug": "seed-bomb",
          "uuid": "Compendium.ptu.moves.Item.b18uGrjFdKGy0rBU"
        },
        {
          "slug": "sleep-talk",
          "uuid": "Compendium.ptu.moves.Item.Jfi9FN77Rplukh7W"
        },
        {
          "slug": "snore",
          "uuid": "Compendium.ptu.moves.Item.RRgY3N3vFTIbzl53"
        },
        {
          "slug": "synthesis",
          "uuid": "Compendium.ptu.moves.Item.zO24D3CxJw7guk2Y"
        },
        {
          "slug": "worry-seed",
          "uuid": "Compendium.ptu.moves.Item.s41RoaO2fbzPVqR6"
        }
      ]
    },
    "skills": {
      "acrobatics": {
        "value": 1,
        "modifier": 0,
        "type": "body"
      },
      "athletics": {
        "value": 4,
        "modifier": 0,
        "type": "body"
      },
      "charm": {
        "value": 2,
        "modifier": 0,
        "type": "spirit"
      },
      "combat": {
        "value": 2,
        "modifier": 0,
        "type": "body"
      },
      "command": {
        "value": 2,
        "modifier": 0,
        "type": "spirit"
      },
      "generalEd": {
        "value": 1,
        "modifier": 0,
        "type": "mind"
      },
      "medicineEd": {
        "value": 1,
        "modifier": 0,
        "type": "mind"
      },
      "occultEd": {
        "value": 1,
        "modifier": 0,
        "type": "mind"
      },
      "pokemonEd": {
        "value": 1,
        "modifier": 0,
        "type": "mind"
      },
      "techEd": {
        "value": 1,
        "modifier": 0,
        "type": "mind"
      },
      "focus": {
        "value": 3,
        "modifier": 0,
        "type": "spirit"
      },
      "guile": {
        "value": 2,
        "modifier": 0,
        "type": "mind"
      },
      "intimidate": {
        "value": 2,
        "modifier": 0,
        "type": "body"
      },
      "intuition": {
        "value": 2,
        "modifier": 0,
        "type": "spirit"
      },
      "perception": {
        "value": 3,
        "modifier": 0,
        "type": "mind"
      },
      "stealth": {
        "value": 4,
        "modifier": 2,
        "type": "body"
      },
      "survival": {
        "value": 2,
        "modifier": 0,
        "type": "body"
      }
    },
    "slug": "delta-crustle-berry",
    "rules": [],
    "source": {
      "value": "Fangame Insurgence Dex"
    },
    "keywords": []
  },
  "img": "/systems/ptu/css/images/icons/dex_icon.png",
  "folder": "PjOQybdSHWn87sdq",
  "name": "Delta Crustle (Berry)",
  "_id": "6pcKrPn2EgXcr0bQ",
  "effects": [],
  "sort": 0,
  "ownership": {
    "default": 0,
    "DsHOL7PqMABKgssN": 3
  },
  "flags": {},
  "_stats": {
    "systemId": "ptu",
    "systemVersion": "4.1.4",
    "coreVersion": "12.317",
    "createdTime": 1689609527590,
    "modifiedTime": 1707761842946,
    "lastModifiedBy": "ODt7FhFvbVjW9f1k"
  },
  "_key": "!items!6pcKrPn2EgXcr0bQ"
}
