{
  "type": "species",
  "system": {
    "schema": {
      "version": 0.11,
      "lastMigration": {
        "datetime": "2023-08-15T11:56:08.125Z",
        "version": {
          "schema": null,
          "foundry": "11.307",
          "system": "0.21"
        }
      }
    },
    "dexentry": "Though they appear intimidating, Emboar are very friendly Pokémon—if a bit impulsive at times. They are very active, spending most of their days either eating or training. Their fists are highly resistant to heat; the red bands on their wrists secrete a highly flammable substance that coat their hands. In combat, Emboar touch their hands to their flaming beards, igniting them and allowing them to pummel opponents with flaming fists. Emboar are adept at many types of combat, switching between using their arms, feet, or entire bodies frequently to bewilder foes. They are capable of cloaking their bodies in flames to ram into foes by using Heat Crash and can also let loose streams of flames from their nostrils. Emboar are protective of their friends, often using their large bodies to shield them from harm. Their fiery beards flare up when they feel strong emotions. Their lively personalities and protective tendencies, along with their great skill in combat, have made Emboar popular Pokémon for many Unova trainers.",
    "number": 500,
    "form": "",
    "stats": {
      "hp": 11,
      "atk": 12,
      "def": 7,
      "spatk": 10,
      "spdef": 7,
      "spd": 7
    },
    "types": [
      "Fire",
      "Fighting"
    ],
    "abilities": {
      "basic": [
        {
          "slug": "blaze",
          "uuid": "Compendium.ptu.abilities.Item.0Oa5Lz4gEIRwlDUD"
        },
        {
          "slug": "thick-fat",
          "uuid": "Compendium.ptu.abilities.Item.g9kAU2J4rkXhNDJv"
        }
      ],
      "advanced": [
        {
          "slug": "gluttony",
          "uuid": "Compendium.ptu.abilities.Item.r5RAP7wiKkOLZ81U"
        },
        {
          "slug": "reckless",
          "uuid": "Compendium.ptu.abilities.Item.rCJBNK2adHEKBYfG"
        }
      ],
      "high": [
        {
          "slug": "bodyguard",
          "uuid": "Compendium.ptu.abilities.Item.8O7o6xH3FIi4RXi9"
        }
      ]
    },
    "evolutions": [
      {
        "uuid": "Compendium.ptu.species.Item.2Ie9Fhs6aoLdwyIP",
        "slug": "tepig",
        "level": 1,
        "other": {
          "restrictions": []
        }
      },
      {
        "uuid": "Compendium.ptu.species.Item.I2yp8smShiavO8ds",
        "slug": "pignite",
        "level": 15,
        "other": {
          "restrictions": []
        }
      },
      {
        "uuid": "Compendium.ptu.species.Item.b7pqXMdyeewZDRie",
        "slug": "emboar",
        "level": 30,
        "other": {
          "restrictions": []
        }
      }
    ],
    "size": {
      "height": 1.6,
      "weight": 150,
      "sizeClass": "Medium",
      "weightClass": 5
    },
    "breeding": {
      "genderRatio": 87.5,
      "eggGroups": [
        "Field"
      ],
      "hatchRate": -1
    },
    "diet": [
      "Omnivore"
    ],
    "habitats": [
      "Forest",
      "Grassland",
      "Mountain"
    ],
    "capabilities": {
      "overland": 7,
      "sky": 0,
      "swim": 4,
      "levitate": 0,
      "burrow": 0,
      "highJump": 1,
      "longJump": 2,
      "power": 8,
      "naturewalk": [
        "Grassland"
      ],
      "other": [
        {
          "slug": "firestarter",
          "uuid": "Compendium.ptu.capabilities.Item.nAIkONF3gtaYfEyX"
        },
        {
          "slug": "heater",
          "uuid": "Compendium.ptu.capabilities.Item.9DQsEtRIDXdw7ICw"
        },
        {
          "slug": "tracker",
          "uuid": "Compendium.ptu.capabilities.Item.W1Zt8pLS50kjTL1d"
        }
      ]
    },
    "moves": {
      "level": [
        {
          "uuid": "Compendium.ptu.moves.Item.6lQy212f7N3GH5KS",
          "slug": "tail-whip",
          "level": 3
        },
        {
          "uuid": "Compendium.ptu.moves.Item.IH2EuCM09nw3lOgQ",
          "slug": "ember",
          "level": 7
        },
        {
          "uuid": "Compendium.ptu.moves.Item.ODezCmXA3509k122",
          "slug": "odor-sleuth",
          "level": 9
        },
        {
          "uuid": "Compendium.ptu.moves.Item.Y5R5mbVcGq6fwoFj",
          "slug": "defense-curl",
          "level": 13
        },
        {
          "uuid": "Compendium.ptu.moves.Item.TeL0p7BkR386XexV",
          "slug": "flame-charge",
          "level": 15
        },
        {
          "uuid": "Compendium.ptu.moves.Item.1C4eSkywCcdopGkD",
          "slug": "smog",
          "level": 20
        },
        {
          "uuid": "Compendium.ptu.moves.Item.nzhedIfXpsZWaEx9",
          "slug": "rollout",
          "level": 23
        },
        {
          "uuid": "Compendium.ptu.moves.Item.rmDcfFfrdq5PgwF9",
          "slug": "take-down",
          "level": 28
        },
        {
          "uuid": "Compendium.ptu.moves.Item.Vbx41b1x1ClrU2pj",
          "slug": "heat-crash",
          "level": 31
        },
        {
          "uuid": "Compendium.ptu.moves.Item.eQqKpKRD5wG1Hg7d",
          "slug": "assurance",
          "level": 38
        },
        {
          "uuid": "Compendium.ptu.moves.Item.m01FTVITfrqlu0Kn",
          "slug": "flamethrower",
          "level": 43
        },
        {
          "uuid": "Compendium.ptu.moves.Item.IeLVMhoSWyAuznBv",
          "slug": "head-smash",
          "level": 50
        },
        {
          "uuid": "Compendium.ptu.moves.Item.sjIa2jm1cHAiMwmY",
          "slug": "roar",
          "level": 55
        },
        {
          "uuid": "Compendium.ptu.moves.Item.VxO7N8CbFaW3889w",
          "slug": "flare-blitz",
          "level": 62
        }
      ],
      "machine": [
        {
          "uuid": "Compendium.ptu.moves.Item.gCofXErMduyn6zwf",
          "slug": "work-up"
        },
        {
          "uuid": "Compendium.ptu.moves.Item.sjIa2jm1cHAiMwmY",
          "slug": "roar"
        },
        {
          "uuid": "Compendium.ptu.moves.Item.eFxRUdqQgdnJybY4",
          "slug": "toxic"
        },
        {
          "uuid": "Compendium.ptu.moves.Item.du6VccHCQ2VjQ0D8",
          "slug": "bulk-up"
        },
        {
          "uuid": "Compendium.ptu.moves.Item.QyDgi8hL1jQLLhld",
          "slug": "hidden-power"
        },
        {
          "uuid": "Compendium.ptu.moves.Item.m787MkYyENqNyGOb",
          "slug": "sunny-day"
        },
        {
          "uuid": "Compendium.ptu.moves.Item.PPcOINwAtEYByNNN",
          "slug": "taunt"
        },
        {
          "uuid": "Compendium.ptu.moves.Item.WV86ctKatPhQpZC3",
          "slug": "hyper-beam"
        },
        {
          "uuid": "Compendium.ptu.moves.Item.HfiQ6I7xp7aGazV0",
          "slug": "protect"
        },
        {
          "uuid": "Compendium.ptu.moves.Item.sMByqeVz0Wq8Ybby",
          "slug": "frustration"
        },
        {
          "uuid": "Compendium.ptu.moves.Item.Oa9NuYFi7yvPQTIO",
          "slug": "solar-beam"
        },
        {
          "uuid": "Compendium.ptu.moves.Item.YG7EABDKQsFjDi8E",
          "slug": "smack-down"
        },
        {
          "uuid": "Compendium.ptu.moves.Item.qQGrbuuO6EcG6b7c",
          "slug": "earthquake"
        },
        {
          "uuid": "Compendium.ptu.moves.Item.eRjK7eB733bE0D8o",
          "slug": "return"
        },
        {
          "uuid": "Compendium.ptu.moves.Item.QD9iT4AII5PpKxab",
          "slug": "brick-break"
        },
        {
          "uuid": "Compendium.ptu.moves.Item.BHmRIX70tqHROfdN",
          "slug": "double-team"
        },
        {
          "uuid": "Compendium.ptu.moves.Item.m01FTVITfrqlu0Kn",
          "slug": "flamethrower"
        },
        {
          "uuid": "Compendium.ptu.moves.Item.2J0IU5MKdpEwtTfM",
          "slug": "fire-blast"
        },
        {
          "uuid": "Compendium.ptu.moves.Item.TYpDbl848dGUkN3q",
          "slug": "rock-tomb"
        },
        {
          "uuid": "Compendium.ptu.moves.Item.QhQ2vUo3KMKo4Xou",
          "slug": "facade"
        },
        {
          "uuid": "Compendium.ptu.moves.Item.TeL0p7BkR386XexV",
          "slug": "flame-charge"
        },
        {
          "uuid": "Compendium.ptu.moves.Item.P0JIeR4lnilvg7K8",
          "slug": "rest"
        },
        {
          "uuid": "Compendium.ptu.moves.Item.0VI0E6oSQYULcSUU",
          "slug": "attract"
        },
        {
          "uuid": "Compendium.ptu.moves.Item.PdslVg2qIvDMDHiA",
          "slug": "low-sweep"
        },
        {
          "uuid": "Compendium.ptu.moves.Item.GgdkAr3gDO6snP7r",
          "slug": "round"
        },
        {
          "uuid": "Compendium.ptu.moves.Item.gOhBiJMpOl84MLaX",
          "slug": "echoed-voice"
        },
        {
          "uuid": "Compendium.ptu.moves.Item.TPm4Ml8gUM4sjXL6",
          "slug": "overheat"
        },
        {
          "uuid": "Compendium.ptu.moves.Item.HU7NSy5rYDet6DbI",
          "slug": "focus-blast"
        },
        {
          "uuid": "Compendium.ptu.moves.Item.Nu3QmPfiZVzOccNU",
          "slug": "scald"
        },
        {
          "uuid": "Compendium.ptu.moves.Item.fDc6STMtfRenewU6",
          "slug": "fling"
        },
        {
          "uuid": "Compendium.ptu.moves.Item.qltGKDIhEJpOqswU",
          "slug": "will-o-wisp"
        },
        {
          "uuid": "Compendium.ptu.moves.Item.WGOQso4iji1XKrdK",
          "slug": "giga-impact"
        },
        {
          "uuid": "Compendium.ptu.moves.Item.K67dXQdgED0HJTut",
          "slug": "stone-edge"
        },
        {
          "uuid": "Compendium.ptu.moves.Item.jn8ej4sQ6o2PuUJx",
          "slug": "gyro-ball"
        },
        {
          "uuid": "Compendium.ptu.moves.Item.J2l5Cmp9LEW7Jvgu",
          "slug": "bulldoze"
        },
        {
          "uuid": "Compendium.ptu.moves.Item.AvGyaqir7qFsEzxk",
          "slug": "rock-slide"
        },
        {
          "uuid": "Compendium.ptu.moves.Item.TFFIb8CygY9dB625",
          "slug": "poison-jab"
        },
        {
          "uuid": "Compendium.ptu.moves.Item.jh2qDsk9mirEzqvu",
          "slug": "grass-knot"
        },
        {
          "uuid": "Compendium.ptu.moves.Item.arxy479cTjkB8mML",
          "slug": "swagger"
        },
        {
          "uuid": "Compendium.ptu.moves.Item.Jfi9FN77Rplukh7W",
          "slug": "sleep-talk"
        },
        {
          "uuid": "Compendium.ptu.moves.Item.IGk8nNBogMKp3seI",
          "slug": "substitute"
        },
        {
          "uuid": "Compendium.ptu.moves.Item.idhhi7YJRDHnUUMR",
          "slug": "wild-charge"
        },
        {
          "uuid": "Compendium.ptu.moves.Item.43i757GW8pptWB5j",
          "slug": "confide"
        }
      ],
      "egg": [],
      "tutor": [
        {
          "uuid": "Compendium.ptu.moves.Item.MVQIN27r61bxzB7J",
          "slug": "arm-thrust-n"
        },
        {
          "uuid": "Compendium.ptu.moves.Item.JfUfttZb9KAdmkZY",
          "slug": "blast-burn"
        },
        {
          "uuid": "Compendium.ptu.moves.Item.PvmLk3AU04nOjH4x",
          "slug": "block"
        },
        {
          "uuid": "Compendium.ptu.moves.Item.Ys1GdaKIZDiaptNB",
          "slug": "covet"
        },
        {
          "uuid": "Compendium.ptu.moves.Item.AZOdMOvyaPYtEXOQ",
          "slug": "endeavor"
        },
        {
          "uuid": "Compendium.ptu.moves.Item.E01AjSiCCXvDiF7E",
          "slug": "fire-pledge"
        },
        {
          "uuid": "Compendium.ptu.moves.Item.EA2vavVCPlHFLvwf",
          "slug": "fire-punch"
        },
        {
          "uuid": "Compendium.ptu.moves.Item.JwDy34HQ8GT4v6Jv",
          "slug": "focus-punch"
        },
        {
          "uuid": "Compendium.ptu.moves.Item.uX0GA4opzRCtDQVY",
          "slug": "hammer-arm-n"
        },
        {
          "uuid": "Compendium.ptu.moves.Item.Z0jlIyTMOL1QXcDb",
          "slug": "heat-wave"
        },
        {
          "uuid": "Compendium.ptu.moves.Item.xhZNseKRJl3pPnTZ",
          "slug": "helping-hand"
        },
        {
          "uuid": "Compendium.ptu.moves.Item.BGJbdXIYaUJJwOQN",
          "slug": "iron-head"
        },
        {
          "uuid": "Compendium.ptu.moves.Item.bpb9SFiI7s9wqGyb",
          "slug": "iron-tail"
        },
        {
          "uuid": "Compendium.ptu.moves.Item.dOMKjZx7flfPZTtV",
          "slug": "low-kick"
        },
        {
          "uuid": "Compendium.ptu.moves.Item.RRgY3N3vFTIbzl53",
          "slug": "snore"
        },
        {
          "uuid": "Compendium.ptu.moves.Item.2sgLgahHycXD5OuT",
          "slug": "stomping-tantrum"
        },
        {
          "uuid": "Compendium.ptu.moves.Item.xwJMUiNv3k0k9VK6",
          "slug": "superpower"
        },
        {
          "uuid": "Compendium.ptu.moves.Item.0gi5EtY9Gq2yZ4eY",
          "slug": "thunder-punch"
        },
        {
          "uuid": "Compendium.ptu.moves.Item.bbYMsmddMV20isEx",
          "slug": "zen-headbutt"
        }
      ]
    },
    "skills": {
      "acrobatics": {
        "value": 2,
        "modifier": 0,
        "type": "body"
      },
      "athletics": {
        "value": 5,
        "modifier": 3,
        "type": "body"
      },
      "charm": {
        "value": 2,
        "modifier": 0,
        "type": "spirit"
      },
      "combat": {
        "value": 4,
        "modifier": 3,
        "type": "body"
      },
      "command": {
        "value": 2,
        "modifier": 0,
        "type": "spirit"
      },
      "generalEd": {
        "value": 1,
        "modifier": 0,
        "type": "mind"
      },
      "medicineEd": {
        "value": 1,
        "modifier": 0,
        "type": "mind"
      },
      "occultEd": {
        "value": 1,
        "modifier": 0,
        "type": "mind"
      },
      "pokemonEd": {
        "value": 1,
        "modifier": 0,
        "type": "mind"
      },
      "techEd": {
        "value": 1,
        "modifier": 0,
        "type": "mind"
      },
      "focus": {
        "value": 4,
        "modifier": 0,
        "type": "spirit"
      },
      "guile": {
        "value": 2,
        "modifier": 0,
        "type": "mind"
      },
      "intimidate": {
        "value": 2,
        "modifier": 0,
        "type": "body"
      },
      "intuition": {
        "value": 2,
        "modifier": 0,
        "type": "spirit"
      },
      "perception": {
        "value": 3,
        "modifier": 0,
        "type": "mind"
      },
      "stealth": {
        "value": 2,
        "modifier": 0,
        "type": "body"
      },
      "survival": {
        "value": 2,
        "modifier": 0,
        "type": "body"
      }
    },
    "slug": "emboar",
    "rules": []
  },
  "img": "/systems/ptu/css/images/icons/dex_icon.png",
  "folder": "dljUGxtO8AR0tERN",
  "name": "Emboar",
  "_id": "b7pqXMdyeewZDRie",
  "effects": [],
  "sort": 68800000,
  "ownership": {
    "default": 0,
    "DsHOL7PqMABKgssN": 3
  },
  "flags": {},
  "_stats": {
    "systemId": "ptu",
    "systemVersion": "4.0.0.beta.4",
    "coreVersion": "11.309",
    "createdTime": 1689609527590,
    "modifiedTime": 1696169282411,
    "lastModifiedBy": "ODt7FhFvbVjW9f1k"
  },
  "_key": "!items!b7pqXMdyeewZDRie"
}