{
  "type": "species",
  "system": {
    "schema": {
      "version": 0.11,
      "lastMigration": {
        "datetime": "2023-08-15T11:56:03.811Z",
        "version": {
          "schema": null,
          "foundry": "11.307",
          "system": "0.21"
        }
      }
    },
    "dexentry": "",
    "number": 3562,
    "form": "",
    "stats": {
      "hp": 6,
      "atk": 6,
      "def": 5,
      "spatk": 7,
      "spdef": 5,
      "spd": 6
    },
    "types": [
      "Water"
    ],
    "abilities": {
      "basic": [
        {
          "slug": "damp",
          "uuid": "Compendium.ptu.abilities.Item.VeCeKD06r2h3Iuyd"
        },
        {
          "slug": "pickup",
          "uuid": "Compendium.ptu.abilities.Item.mPHOvZFG51lOB2Tf"
        }
      ],
      "advanced": [
        {
          "slug": "swift-swim",
          "uuid": "Compendium.ptu.abilities.Item.RK51P3bQWpC6Ioz2"
        },
        {
          "slug": "bodyguard",
          "uuid": "Compendium.ptu.abilities.Item.8O7o6xH3FIi4RXi9"
        }
      ],
      "high": [
        {
          "slug": "celebrate",
          "uuid": "Compendium.ptu.abilities.Item.xhjgbopRyNS1nOHB"
        }
      ]
    },
    "evolutions": [
      {
        "level": 1,
        "uuid": "Compendium.ptu.species.Item.2I1ahLUUygvjzW2B",
        "slug": "pawter",
        "other": {
          "restrictions": []
        }
      },
      {
        "level": 30,
        "uuid": "Compendium.ptu.species.Item.CApDiu9mEUpBxLoW",
        "slug": "hurricanine",
        "other": {
          "restrictions": []
        }
      }
    ],
    "size": {
      "height": 0.6,
      "weight": 9.1,
      "sizeClass": "Small",
      "weightClass": 1
    },
    "breeding": {
      "genderRatio": 50,
      "eggGroups": [
        "Field",
        "Water 1"
      ],
      "hatchRate": 10
    },
    "diet": [
      "Omnivore"
    ],
    "habitats": [
      "Beach",
      "Grassland"
    ],
    "capabilities": {
      "overland": 4,
      "sky": 0,
      "swim": 4,
      "levitate": 0,
      "burrow": 0,
      "highJump": 1,
      "longJump": 1,
      "power": 3,
      "naturewalk": [
        "Ocean"
      ],
      "other": [
        {
          "slug": "fountain",
          "uuid": "Compendium.ptu.capabilities.Item.ut911FJQTWb21u98"
        },
        {
          "slug": "premonition",
          "uuid": "Compendium.ptu.capabilities.Item.2DN9tE1jdI8MdMcU"
        },
        {
          "slug": "underdog",
          "uuid": "Compendium.ptu.capabilities.Item.AIbbzjfDZix8YFkU"
        }
      ]
    },
    "moves": {
      "level": [
        {
          "slug": "tackle",
          "uuid": "Compendium.ptu.moves.Item.50Vtl0u0jPevwY4K",
          "level": 1
        },
        {
          "slug": "water-sport",
          "uuid": "Compendium.ptu.moves.Item.aQC3OZK3LUV4UHj2",
          "level": 1
        },
        {
          "slug": "leer",
          "uuid": "Compendium.ptu.moves.Item.XQOEuOenSzYNz4eO",
          "level": 3
        },
        {
          "slug": "odor-sleuth",
          "uuid": "Compendium.ptu.moves.Item.ODezCmXA3509k122",
          "level": 6
        },
        {
          "slug": "water-gun",
          "uuid": "Compendium.ptu.moves.Item.rYLmG0KWrwYOCkmR",
          "level": 9
        },
        {
          "slug": "howl",
          "uuid": "Compendium.ptu.moves.Item.IcjwAnfajBTDL3IF",
          "level": 11
        },
        {
          "slug": "bite",
          "uuid": "Compendium.ptu.moves.Item.QMaJ91E3XBatUcV9",
          "level": 14
        },
        {
          "slug": "charge",
          "uuid": "Compendium.ptu.moves.Item.qRvLgOrsmdXEsBsU",
          "level": 17
        },
        {
          "slug": "water-pulse",
          "uuid": "Compendium.ptu.moves.Item.9TnRLGZ6WIGqIeQ4",
          "level": 19
        },
        {
          "slug": "baton-pass",
          "uuid": "Compendium.ptu.moves.Item.uZjoE8y3gbmlRVcc",
          "level": 22
        },
        {
          "slug": "take-down",
          "uuid": "Compendium.ptu.moves.Item.rmDcfFfrdq5PgwF9",
          "level": 25
        },
        {
          "slug": "roar",
          "uuid": "Compendium.ptu.moves.Item.sjIa2jm1cHAiMwmY",
          "level": 27
        },
        {
          "slug": "ice-fang",
          "uuid": "Compendium.ptu.moves.Item.uGIN68MryZnqXa5w",
          "level": 30
        },
        {
          "slug": "mist",
          "uuid": "Compendium.ptu.moves.Item.uaOHYAjzdGsqGBJ0",
          "level": 33
        },
        {
          "slug": "muddy-water",
          "uuid": "Compendium.ptu.moves.Item.updKSTwGuQaZfbTk",
          "level": 35
        },
        {
          "slug": "aqua-ring",
          "uuid": "Compendium.ptu.moves.Item.ywYeIhxlrHb9gOP1",
          "level": 38
        },
        {
          "slug": "crunch",
          "uuid": "Compendium.ptu.moves.Item.5uY1ltFWijN07CKe",
          "level": 41
        },
        {
          "slug": "aqua-tail",
          "uuid": "Compendium.ptu.moves.Item.O8DwOJXqhrynxm8B",
          "level": 43
        },
        {
          "slug": "soak",
          "uuid": "Compendium.ptu.moves.Item.sKWmTZ2uB6fKrhmo",
          "level": 46
        }
      ],
      "machine": [
        {
          "slug": "work-up",
          "uuid": "Compendium.ptu.moves.Item.gCofXErMduyn6zwf"
        },
        {
          "slug": "roar",
          "uuid": "Compendium.ptu.moves.Item.sjIa2jm1cHAiMwmY"
        },
        {
          "slug": "toxic",
          "uuid": "Compendium.ptu.moves.Item.eFxRUdqQgdnJybY4"
        },
        {
          "slug": "hail",
          "uuid": "Compendium.ptu.moves.Item.pRtupyIihgfCW09B"
        },
        {
          "slug": "hidden-power",
          "uuid": "Compendium.ptu.moves.Item.QyDgi8hL1jQLLhld"
        },
        {
          "slug": "ice-beam",
          "uuid": "Compendium.ptu.moves.Item.ipZPqONhX7WsWJ5U"
        },
        {
          "slug": "blizzard",
          "uuid": "Compendium.ptu.moves.Item.OaCO337ux9X8zQ2s"
        },
        {
          "slug": "protect",
          "uuid": "Compendium.ptu.moves.Item.HfiQ6I7xp7aGazV0"
        },
        {
          "slug": "rain-dance",
          "uuid": "Compendium.ptu.moves.Item.TQrk7QpDTMSD7Ycz"
        },
        {
          "slug": "frustration",
          "uuid": "Compendium.ptu.moves.Item.tkATQl42vxqWDfjd"
        },
        {
          "slug": "return",
          "uuid": "Compendium.ptu.moves.Item.eRjK7eB733bE0D8o"
        },
        {
          "slug": "double-team",
          "uuid": "Compendium.ptu.moves.Item.BHmRIX70tqHROfdN"
        },
        {
          "slug": "facade",
          "uuid": "Compendium.ptu.moves.Item.QhQ2vUo3KMKo4Xou"
        },
        {
          "slug": "rest",
          "uuid": "Compendium.ptu.moves.Item.P0JIeR4lnilvg7K8"
        },
        {
          "slug": "attract",
          "uuid": "Compendium.ptu.moves.Item.0VI0E6oSQYULcSUU"
        },
        {
          "slug": "thief",
          "uuid": "Compendium.ptu.moves.Item.cu9K3c625G2F54lh"
        },
        {
          "slug": "round",
          "uuid": "Compendium.ptu.moves.Item.GgdkAr3gDO6snP7r"
        },
        {
          "slug": "payback",
          "uuid": "Compendium.ptu.moves.Item.8frJ1rnKqBmGvKC0"
        },
        {
          "slug": "bulldoze",
          "uuid": "Compendium.ptu.moves.Item.J2l5Cmp9LEW7Jvgu"
        },
        {
          "slug": "swagger",
          "uuid": "Compendium.ptu.moves.Item.arxy479cTjkB8mML"
        },
        {
          "slug": "sleep-talk",
          "uuid": "Compendium.ptu.moves.Item.Jfi9FN77Rplukh7W"
        },
        {
          "slug": "substitute",
          "uuid": "Compendium.ptu.moves.Item.IGk8nNBogMKp3seI"
        },
        {
          "slug": "wild-charge",
          "uuid": "Compendium.ptu.moves.Item.idhhi7YJRDHnUUMR"
        },
        {
          "slug": "surf",
          "uuid": "Compendium.ptu.moves.Item.pRxBTVSGS7ScdK5s"
        },
        {
          "slug": "snarl",
          "uuid": "Compendium.ptu.moves.Item.jVruXIDWy3HEHAeA"
        },
        {
          "slug": "waterfall",
          "uuid": "Compendium.ptu.moves.Item.72Gli6hv7dk4QRdN"
        },
        {
          "slug": "confide",
          "uuid": "Compendium.ptu.moves.Item.43i757GW8pptWB5j"
        }
      ],
      "egg": [
        {
          "slug": "crunch",
          "uuid": "Compendium.ptu.moves.Item.5uY1ltFWijN07CKe"
        },
        {
          "slug": "hydro-pump",
          "uuid": "Compendium.ptu.moves.Item.oRu76Vk1LfE93pky"
        },
        {
          "slug": "last-resort",
          "uuid": "Compendium.ptu.moves.Item.syEhvBKtqQTBqyct"
        },
        {
          "slug": "lick",
          "uuid": "Compendium.ptu.moves.Item.6ePYnDDvYpss2MsY"
        },
        {
          "slug": "mist",
          "uuid": "Compendium.ptu.moves.Item.uaOHYAjzdGsqGBJ0"
        }
      ],
      "tutor": [
        {
          "slug": "aqua-tail",
          "uuid": "Compendium.ptu.moves.Item.O8DwOJXqhrynxm8B"
        },
        {
          "slug": "brine",
          "uuid": "Compendium.ptu.moves.Item.5ORKWU9EYYyzJOaH"
        },
        {
          "slug": "dive",
          "uuid": "Compendium.ptu.moves.Item.5P4ZKecoBzCd8vh5"
        },
        {
          "slug": "double-edge",
          "uuid": "Compendium.ptu.moves.Item.7Gi57ZcOWjyjhU0A"
        },
        {
          "slug": "endeavor",
          "uuid": "Compendium.ptu.moves.Item.AZOdMOvyaPYtEXOQ"
        },
        {
          "slug": "endure",
          "uuid": "Compendium.ptu.moves.Item.IAFYzSRQGxZM1SSQ"
        },
        {
          "slug": "helping-hand",
          "uuid": "Compendium.ptu.moves.Item.xhZNseKRJl3pPnTZ"
        },
        {
          "slug": "icy-wind",
          "uuid": "Compendium.ptu.moves.Item.OI05tbugvNMMOqmc"
        },
        {
          "slug": "last-resort",
          "uuid": "Compendium.ptu.moves.Item.syEhvBKtqQTBqyct"
        },
        {
          "slug": "liquidation",
          "uuid": "Compendium.ptu.moves.Item.iRpfWZ1PSCAeyUEX"
        },
        {
          "slug": "mud-slap",
          "uuid": "Compendium.ptu.moves.Item.rDlHKWGG9k3AxIlP"
        },
        {
          "slug": "secret-power",
          "uuid": "Compendium.ptu.moves.Item.6Q0qjfHVNHd5fsec"
        },
        {
          "slug": "snore",
          "uuid": "Compendium.ptu.moves.Item.RRgY3N3vFTIbzl53"
        },
        {
          "slug": "super-fang",
          "uuid": "Compendium.ptu.moves.Item.foVUAPgmU09qFHrb"
        },
        {
          "slug": "swift",
          "uuid": "Compendium.ptu.moves.Item.MLCGs5okqB4BLJKc"
        },
        {
          "slug": "uproar",
          "uuid": "Compendium.ptu.moves.Item.Si0MaGpUCvDBY8Gd"
        },
        {
          "slug": "water-pulse",
          "uuid": "Compendium.ptu.moves.Item.9TnRLGZ6WIGqIeQ4"
        }
      ]
    },
    "skills": {
      "acrobatics": {
        "value": 2,
        "modifier": 0,
        "type": "body"
      },
      "athletics": {
        "value": 3,
        "modifier": 0,
        "type": "body"
      },
      "charm": {
        "value": 2,
        "modifier": 0,
        "type": "spirit"
      },
      "combat": {
        "value": 3,
        "modifier": 0,
        "type": "body"
      },
      "command": {
        "value": 2,
        "modifier": 0,
        "type": "spirit"
      },
      "generalEd": {
        "value": 1,
        "modifier": 0,
        "type": "mind"
      },
      "medicineEd": {
        "value": 1,
        "modifier": 0,
        "type": "mind"
      },
      "occultEd": {
        "value": 1,
        "modifier": 0,
        "type": "mind"
      },
      "pokemonEd": {
        "value": 1,
        "modifier": 0,
        "type": "mind"
      },
      "techEd": {
        "value": 1,
        "modifier": 0,
        "type": "mind"
      },
      "focus": {
        "value": 3,
        "modifier": 0,
        "type": "spirit"
      },
      "guile": {
        "value": 2,
        "modifier": 0,
        "type": "mind"
      },
      "intimidate": {
        "value": 2,
        "modifier": 0,
        "type": "body"
      },
      "intuition": {
        "value": 2,
        "modifier": 0,
        "type": "spirit"
      },
      "perception": {
        "value": 3,
        "modifier": 0,
        "type": "mind"
      },
      "stealth": {
        "value": 3,
        "modifier": 0,
        "type": "body"
      },
      "survival": {
        "value": 2,
        "modifier": 0,
        "type": "body"
      }
    },
    "slug": "pawter",
    "rules": [],
    "source": {
      "value": "Fangame Sage Dex"
    },
    "keywords": []
  },
  "img": "/systems/ptu/css/images/icons/dex_icon.png",
  "folder": "CMymFngAhNsaPlS5",
  "name": "Pawter",
  "_id": "2I1ahLUUygvjzW2B",
  "effects": [],
  "sort": 0,
  "ownership": {
    "default": 0,
    "DsHOL7PqMABKgssN": 3
  },
  "flags": {},
  "_stats": {
    "systemId": "ptu",
    "systemVersion": "4.1.4",
    "coreVersion": "12.316",
    "createdTime": 1689609527590,
    "modifiedTime": 1707761842946,
    "lastModifiedBy": "ODt7FhFvbVjW9f1k"
  },
  "_key": "!items!2I1ahLUUygvjzW2B"
}
